{
  "name": "支出事项设置",
  "headers": [
    "事项编码",
    "事项名称",
    "事项分类",
    "是否末级",
    "支出明细",
    "归口部门",
    "归口代编",
    "资本性支出",
    "明细表单",
    "功能分类科目",
    "部门经济分类",
    "政府经济分类",
    "现金流量",
    "发布方式",
    "表单类型",
    "开支标准",
    "事项定义"
  ],
  "records": [
    {
      "事项编码": "1001",
      "事项名称": "人员经费",
      "事项分类": "基本经费",
      "是否末级": "否",
      "支出明细": "金额",
      "归口部门": "院办",
      "归口代编": "是",
      "资本性支出": "",
      "明细表单": "无",
      "功能分类科目": "综合医院",
      "部门经济分类": "",
      "政府经济分类": "",
      "现金流量": "",
      "发布方式": "",
      "表单类型": "",
      "开支标准": "",
      "事项定义": ""
    },
    {
      "事项编码": "100101",
      "事项名称": "工资福利支出",
      "事项分类": "基本经费",
      "是否末级": "否",
      "支出明细": "金额",
      "归口部门": "院办",
      "归口代编": "是",
      "资本性支出": "",
      "明细表单": "无",
      "功能分类科目": "综合医院",
      "部门经济分类": "",
      "政府经济分类": "",
      "现金流量": "",
      "发布方式": "",
      "表单类型": "",
      "开支标准": "",
      "事项定义": ""
    },
    {
      "事项编码": "10010101",
      "事项名称": "全国工资",
      "事项分类": "基本经费",
      "是否末级": "否",
      "支出明细": "金额",
      "归口部门": "院办",
      "归口代编": "是",
      "资本性支出": "否",
      "明细表单": "无",
      "功能分类科目": "综合医院",
      "部门经济分类": "",
      "政府经济分类": "",
      "现金流量": "",
      "发布方式": "一次性发布",
      "表单类型": "一般经费",
      "开支标准": "",
      "事项定义": ""
    },
    {
      "事项编码": "1001010101",
      "事项名称": "岗位工资",
      "事项分类": "基本经费",
      "是否末级": "是",
      "支出明细": "金额",
      "归口部门": "院办",
      "归口代编": "是",
      "资本性支出": "否",
      "明细表单": "工会经费",
      "功能分类科目": "综合医院",
      "部门经济分类": "  基本工资",
      "政府经济分类": "",
      "现金流量": "",
      "发布方式": "一次性发布",
      "表单类型": "一般经费",
      "开支标准": "",
      "事项定义": ""
    },
    {
      "事项编码": "1001010102",
      "事项名称": "薪级工资",
      "事项分类": "基本经费",
      "是否末级": "是",
      "支出明细": "金额",
      "归口部门": "院办",
      "归口代编": "是",
      "资本性支出": "否",
      "明细表单": "无",
      "功能分类科目": "综合医院",
      "部门经济分类": "  基本工资",
      "政府经济分类": "",
      "现金流量": "",
      "发布方式": "一次性发布",
      "表单类型": "一般经费",
      "开支标准": "",
      "事项定义": ""
    },
    {
      "事项编码": "10010102",
      "事项名称": "基础性绩效工资",
      "事项分类": "基本经费",
      "是否末级": "否",
      "支出明细": "金额",
      "归口部门": "院办",
      "归口代编": "是",
      "资本性支出": "",
      "明细表单": "无",
      "功能分类科目": "综合医院",
      "部门经济分类": "",
      "政府经济分类": "",
      "现金流量": "",
      "发布方式": "",
      "表单类型": "",
      "开支标准": "",
      "事项定义": ""
    },
    {
      "事项编码": "1001010201",
      "事项名称": "特区津贴",
      "事项分类": "基本经费",
      "是否末级": "是",
      "支出明细": "金额",
      "归口部门": "院办",
      "归口代编": "是",
      "资本性支出": "否",
      "明细表单": "无",
      "功能分类科目": "综合医院",
      "部门经济分类": "  津贴补贴",
      "政府经济分类": "",
      "现金流量": "",
      "发布方式": "一次性发布",
      "表单类型": "一般经费",
      "开支标准": "",
      "事项定义": ""
    },
    {
      "事项编码": "1001010202",
      "事项名称": "基础津贴",
      "事项分类": "基本经费",
      "是否末级": "是",
      "支出明细": "金额",
      "归口部门": "院办",
      "归口代编": "是",
      "资本性支出": "否",
      "明细表单": "无",
      "功能分类科目": "综合医院",
      "部门经济分类": "  津贴补贴",
      "政府经济分类": "",
      "现金流量": "",
      "发布方式": "一次性发布",
      "表单类型": "一般经费",
      "开支标准": "",
      "事项定义": ""
    },
    {
      "事项编码": "10010103",
      "事项名称": "特殊岗位津贴",
      "事项分类": "基本经费",
      "是否末级": "是",
      "支出明细": "金额",
      "归口部门": "院办",
      "归口代编": "是",
      "资本性支出": "否",
      "明细表单": "无",
      "功能分类科目": "综合医院",
      "部门经济分类": "  津贴补贴",
      "政府经济分类": "",
      "现金流量": "",
      "发布方式": "一次性发布",
      "表单类型": "一般经费",
      "开支标准": "",
      "事项定义": ""
    },
    {
      "事项编码": "10010104",
      "事项名称": "社会保险缴费",
      "事项分类": "基本经费",
      "是否末级": "是",
      "支出明细": "金额",
      "归口部门": "院办",
      "归口代编": "是",
      "资本性支出": "否",
      "明细表单": "无",
      "功能分类科目": "综合医院",
      "部门经济分类": "  社会保障缴费",
      "政府经济分类": "",
      "现金流量": "",
      "发布方式": "一次性发布",
      "表单类型": "一般经费",
      "开支标准": "",
      "事项定义": ""
    },
    {
      "事项编码": "10010106",
      "事项名称": "奖励性绩效工资",
      "事项分类": "基本经费",
      "是否末级": "是",
      "支出明细": "金额",
      "归口部门": "院办",
      "归口代编": "是",
      "资本性支出": "否",
      "明细表单": "无",
      "功能分类科目": "综合医院",
      "部门经济分类": "  绩效工资",
      "政府经济分类": "",
      "现金流量": "",
      "发布方式": "一次性发布",
      "表单类型": "一般经费",
      "开支标准": "",
      "事项定义": ""
    },
    {
      "事项编码": "10010107",
      "事项名称": "其他工资福利支出",
      "事项分类": "基本经费",
      "是否末级": "是",
      "支出明细": "金额",
      "归口部门": "院办",
      "归口代编": "是",
      "资本性支出": "否",
      "明细表单": "无",
      "功能分类科目": "综合医院",
      "部门经济分类": "  其他工资福利支出",
      "政府经济分类": "",
      "现金流量": "",
      "发布方式": "一次性发布",
      "表单类型": "一般经费",
      "开支标准": "",
      "事项定义": ""
    },
    {
      "事项编码": "100102",
      "事项名称": "对个人和家庭补助",
      "事项分类": "基本经费",
      "是否末级": "否",
      "支出明细": "金额",
      "归口部门": "院办",
      "归口代编": "是",
      "资本性支出": "",
      "明细表单": "无",
      "功能分类科目": "综合医院",
      "部门经济分类": "",
      "政府经济分类": "",
      "现金流量": "",
      "发布方式": "",
      "表单类型": "",
      "开支标准": "",
      "事项定义": ""
    },
    {
      "事项编码": "10010201",
      "事项名称": "离休费",
      "事项分类": "基本经费",
      "是否末级": "是",
      "支出明细": "数量单价",
      "归口部门": "院办",
      "归口代编": "是",
      "资本性支出": "否",
      "明细表单": "无",
      "功能分类科目": "综合医院",
      "部门经济分类": "  离休费",
      "政府经济分类": "",
      "现金流量": "",
      "发布方式": "一次性发布",
      "表单类型": "一般经费",
      "开支标准": "",
      "事项定义": ""
    },
    {
      "事项编码": "10010202",
      "事项名称": "退休费",
      "事项分类": "基本经费",
      "是否末级": "是",
      "支出明细": "金额",
      "归口部门": "院办",
      "归口代编": "是",
      "资本性支出": "否",
      "明细表单": "无",
      "功能分类科目": "综合医院",
      "部门经济分类": "  退休费",
      "政府经济分类": "",
      "现金流量": "",
      "发布方式": "一次性发布",
      "表单类型": "一般经费",
      "开支标准": "",
      "事项定义": ""
    },
    {
      "事项编码": "10010203",
      "事项名称": "退职(役)费",
      "事项分类": "基本经费",
      "是否末级": "是",
      "支出明细": "金额",
      "归口部门": "院办",
      "归口代编": "是",
      "资本性支出": "否",
      "明细表单": "无",
      "功能分类科目": "综合医院",
      "部门经济分类": "  退职（役）费",
      "政府经济分类": "",
      "现金流量": "",
      "发布方式": "一次性发布",
      "表单类型": "一般经费",
      "开支标准": "",
      "事项定义": ""
    },
    {
      "事项编码": "10010204",
      "事项名称": "抚恤金",
      "事项分类": "基本经费",
      "是否末级": "是",
      "支出明细": "金额",
      "归口部门": "院办",
      "归口代编": "是",
      "资本性支出": "否",
      "明细表单": "无",
      "功能分类科目": "综合医院",
      "部门经济分类": "  抚恤金",
      "政府经济分类": "",
      "现金流量": "",
      "发布方式": "一次性发布",
      "表单类型": "一般经费",
      "开支标准": "",
      "事项定义": ""
    },
    {
      "事项编码": "10010205",
      "事项名称": "生活补助",
      "事项分类": "基本经费",
      "是否末级": "是",
      "支出明细": "金额",
      "归口部门": "院办",
      "归口代编": "是",
      "资本性支出": "否",
      "明细表单": "无",
      "功能分类科目": "综合医院",
      "部门经济分类": "  生活补助",
      "政府经济分类": "",
      "现金流量": "",
      "发布方式": "一次性发布",
      "表单类型": "一般经费",
      "开支标准": "",
      "事项定义": ""
    },
    {
      "事项编码": "10010206",
      "事项名称": "救济费",
      "事项分类": "基本经费",
      "是否末级": "是",
      "支出明细": "金额",
      "归口部门": "院办",
      "归口代编": "是",
      "资本性支出": "否",
      "明细表单": "无",
      "功能分类科目": "综合医院",
      "部门经济分类": "  救济费",
      "政府经济分类": "",
      "现金流量": "",
      "发布方式": "一次性发布",
      "表单类型": "一般经费",
      "开支标准": "",
      "事项定义": ""
    },
    {
      "事项编码": "10010207",
      "事项名称": "助学金",
      "事项分类": "基本经费",
      "是否末级": "是",
      "支出明细": "金额",
      "归口部门": "院办",
      "归口代编": "是",
      "资本性支出": "否",
      "明细表单": "无",
      "功能分类科目": "综合医院",
      "部门经济分类": "  助学金",
      "政府经济分类": "",
      "现金流量": "",
      "发布方式": "一次性发布",
      "表单类型": "一般经费",
      "开支标准": "",
      "事项定义": ""
    },
    {
      "事项编码": "10010208",
      "事项名称": "奖励金",
      "事项分类": "基本经费",
      "是否末级": "是",
      "支出明细": "金额",
      "归口部门": "院办",
      "归口代编": "是",
      "资本性支出": "否",
      "明细表单": "无",
      "功能分类科目": "综合医院",
      "部门经济分类": "  奖励金",
      "政府经济分类": "",
      "现金流量": "",
      "发布方式": "一次性发布",
      "表单类型": "一般经费",
      "开支标准": "",
      "事项定义": ""
    },
    {
      "事项编码": "10010209",
      "事项名称": "生产补贴",
      "事项分类": "基本经费",
      "是否末级": "是",
      "支出明细": "金额",
      "归口部门": "院办",
      "归口代编": "是",
      "资本性支出": "否",
      "明细表单": "无",
      "功能分类科目": "综合医院",
      "部门经济分类": "  生产补贴",
      "政府经济分类": "",
      "现金流量": "",
      "发布方式": "一次性发布",
      "表单类型": "一般经费",
      "开支标准": "",
      "事项定义": ""
    },
    {
      "事项编码": "10010210",
      "事项名称": "住房公积金",
      "事项分类": "基本经费",
      "是否末级": "是",
      "支出明细": "金额",
      "归口部门": "院办",
      "归口代编": "是",
      "资本性支出": "否",
      "明细表单": "无",
      "功能分类科目": "综合医院",
      "部门经济分类": "  住房公积金",
      "政府经济分类": "",
      "现金流量": "",
      "发布方式": "一次性发布",
      "表单类型": "一般经费",
      "开支标准": "",
      "事项定义": ""
    },
    {
      "事项编码": "10010211",
      "事项名称": "提租补贴",
      "事项分类": "基本经费",
      "是否末级": "是",
      "支出明细": "金额",
      "归口部门": "院办",
      "归口代编": "是",
      "资本性支出": "否",
      "明细表单": "无",
      "功能分类科目": "综合医院",
      "部门经济分类": "  提租补贴",
      "政府经济分类": "",
      "现金流量": "",
      "发布方式": "一次性发布",
      "表单类型": "一般经费",
      "开支标准": "",
      "事项定义": ""
    },
    {
      "事项编码": "10010212",
      "事项名称": "购房补贴",
      "事项分类": "基本经费",
      "是否末级": "是",
      "支出明细": "金额",
      "归口部门": "院办",
      "归口代编": "是",
      "资本性支出": "否",
      "明细表单": "无",
      "功能分类科目": "综合医院",
      "部门经济分类": "  购房补贴",
      "政府经济分类": "",
      "现金流量": "",
      "发布方式": "一次性发布",
      "表单类型": "一般经费",
      "开支标准": "",
      "事项定义": ""
    },
    {
      "事项编码": "10010213",
      "事项名称": "独生子女补助",
      "事项分类": "基本经费",
      "是否末级": "是",
      "支出明细": "金额",
      "归口部门": "院办",
      "归口代编": "是",
      "资本性支出": "否",
      "明细表单": "无",
      "功能分类科目": "综合医院",
      "部门经济分类": "  其他对个人和家庭的补助支出",
      "政府经济分类": "",
      "现金流量": "",
      "发布方式": "一次性发布",
      "表单类型": "一般经费",
      "开支标准": "",
      "事项定义": ""
    },
    {
      "事项编码": "10010214",
      "事项名称": "计划生育奖",
      "事项分类": "基本经费",
      "是否末级": "是",
      "支出明细": "金额",
      "归口部门": "院办",
      "归口代编": "是",
      "资本性支出": "否",
      "明细表单": "无",
      "功能分类科目": "综合医院",
      "部门经济分类": "  其他对个人和家庭的补助支出",
      "政府经济分类": "",
      "现金流量": "",
      "发布方式": "一次性发布",
      "表单类型": "一般经费",
      "开支标准": "",
      "事项定义": ""
    },
    {
      "事项编码": "10010215",
      "事项名称": "医疗费",
      "事项分类": "基本经费",
      "是否末级": "是",
      "支出明细": "金额",
      "归口部门": "院办",
      "归口代编": "是",
      "资本性支出": "否",
      "明细表单": "无",
      "功能分类科目": "综合医院",
      "部门经济分类": "  医疗费",
      "政府经济分类": "",
      "现金流量": "",
      "发布方式": "一次性发布",
      "表单类型": "一般经费",
      "开支标准": "",
      "事项定义": ""
    },
    {
      "事项编码": "10010216",
      "事项名称": "家属统筹医疗",
      "事项分类": "基本经费",
      "是否末级": "是",
      "支出明细": "金额",
      "归口部门": "院办",
      "归口代编": "是",
      "资本性支出": "否",
      "明细表单": "无",
      "功能分类科目": "综合医院",
      "部门经济分类": "  其他对个人和家庭的补助支出",
      "政府经济分类": "",
      "现金流量": "",
      "发布方式": "一次性发布",
      "表单类型": "一般经费",
      "开支标准": "",
      "事项定义": ""
    },
    {
      "事项编码": "10010217",
      "事项名称": "患者困难补助",
      "事项分类": "基本经费",
      "是否末级": "是",
      "支出明细": "金额",
      "归口部门": "院办",
      "归口代编": "是",
      "资本性支出": "否",
      "明细表单": "无",
      "功能分类科目": "综合医院",
      "部门经济分类": "  其他对个人和家庭的补助支出",
      "政府经济分类": "",
      "现金流量": "",
      "发布方式": "一次性发布",
      "表单类型": "一般经费",
      "开支标准": "",
      "事项定义": ""
    },
    {
      "事项编码": "10010218",
      "事项名称": "探亲路费",
      "事项分类": "基本经费",
      "是否末级": "是",
      "支出明细": "金额",
      "归口部门": "院办",
      "归口代编": "是",
      "资本性支出": "否",
      "明细表单": "无",
      "功能分类科目": "综合医院",
      "部门经济分类": "  其他对个人和家庭的补助支出",
      "政府经济分类": "",
      "现金流量": "",
      "发布方式": "一次性发布",
      "表单类型": "一般经费",
      "开支标准": "",
      "事项定义": ""
    },
    {
      "事项编码": "10010219",
      "事项名称": "其他对个人和家庭补助",
      "事项分类": "基本经费",
      "是否末级": "是",
      "支出明细": "金额",
      "归口部门": "院办",
      "归口代编": "是",
      "资本性支出": "否",
      "明细表单": "无",
      "功能分类科目": "综合医院",
      "部门经济分类": "  其他对个人和家庭的补助支出",
      "政府经济分类": "",
      "现金流量": "",
      "发布方式": "一次性发布",
      "表单类型": "一般经费",
      "开支标准": "",
      "事项定义": ""
    },
    {
      "事项编码": "10010231",
      "事项名称": "员工补贴",
      "事项分类": "基本经费",
      "是否末级": "是",
      "支出明细": "金额",
      "归口部门": "口腔科",
      "归口代编": "否",
      "资本性支出": "否",
      "明细表单": "设备购置",
      "功能分类科目": "",
      "部门经济分类": "",
      "政府经济分类": "",
      "现金流量": "",
      "发布方式": "一次性发布",
      "表单类型": "一般经费",
      "开支标准": "",
      "事项定义": ""
    },
    {
      "事项编码": "1002",
      "事项名称": "购置商品支出",
      "事项分类": "基本经费",
      "是否末级": "否",
      "支出明细": "金额",
      "归口部门": "药剂科",
      "归口代编": "",
      "资本性支出": "",
      "明细表单": "无",
      "功能分类科目": "综合医院",
      "部门经济分类": "",
      "政府经济分类": "",
      "现金流量": "",
      "发布方式": "",
      "表单类型": "",
      "开支标准": "",
      "事项定义": ""
    },
    {
      "事项编码": "100201",
      "事项名称": "卫生材料费",
      "事项分类": "基本经费",
      "是否末级": "否",
      "支出明细": "金额",
      "归口部门": "药剂科",
      "归口代编": "否",
      "资本性支出": "",
      "明细表单": "无",
      "功能分类科目": "综合医院",
      "部门经济分类": "",
      "政府经济分类": "",
      "现金流量": "",
      "发布方式": "",
      "表单类型": "",
      "开支标准": "",
      "事项定义": ""
    },
    {
      "事项编码": "10020101",
      "事项名称": "血费",
      "事项分类": "基本经费",
      "是否末级": "是",
      "支出明细": "金额",
      "归口部门": "医务科",
      "归口代编": "否",
      "资本性支出": "否",
      "明细表单": "信息化项目",
      "功能分类科目": "综合医院",
      "部门经济分类": "  专用材料费",
      "政府经济分类": "",
      "现金流量": "",
      "发布方式": "一次性发布",
      "表单类型": "一般经费",
      "开支标准": "",
      "事项定义": ""
    },
    {
      "事项编码": "10020102",
      "事项名称": "氧气费",
      "事项分类": "基本经费",
      "是否末级": "是",
      "支出明细": "金额",
      "归口部门": "药剂科",
      "归口代编": "否",
      "资本性支出": "否",
      "明细表单": "无",
      "功能分类科目": "综合医院",
      "部门经济分类": "  专用材料费",
      "政府经济分类": "",
      "现金流量": "",
      "发布方式": "一次性发布",
      "表单类型": "一般经费",
      "开支标准": "",
      "事项定义": ""
    },
    {
      "事项编码": "10020103",
      "事项名称": "放射材料",
      "事项分类": "基本经费",
      "是否末级": "是",
      "支出明细": "金额",
      "归口部门": "药剂科",
      "归口代编": "否",
      "资本性支出": "否",
      "明细表单": "无",
      "功能分类科目": "综合医院",
      "部门经济分类": "  专用材料费",
      "政府经济分类": "",
      "现金流量": "",
      "发布方式": "一次性发布",
      "表单类型": "一般经费",
      "开支标准": "",
      "事项定义": ""
    },
    {
      "事项编码": "10020104",
      "事项名称": "化验材料",
      "事项分类": "基本经费",
      "是否末级": "是",
      "支出明细": "金额",
      "归口部门": "药剂科",
      "归口代编": "否",
      "资本性支出": "否",
      "明细表单": "无",
      "功能分类科目": "综合医院",
      "部门经济分类": "  专用材料费",
      "政府经济分类": "",
      "现金流量": "",
      "发布方式": "一次性发布",
      "表单类型": "一般经费",
      "开支标准": "",
      "事项定义": ""
    },
    {
      "事项编码": "10020105",
      "事项名称": "口腔材料",
      "事项分类": "基本经费",
      "是否末级": "是",
      "支出明细": "金额",
      "归口部门": "药剂科",
      "归口代编": "否",
      "资本性支出": "否",
      "明细表单": "无",
      "功能分类科目": "综合医院",
      "部门经济分类": "  专用材料费",
      "政府经济分类": "",
      "现金流量": "",
      "发布方式": "一次性发布",
      "表单类型": "一般经费",
      "开支标准": "",
      "事项定义": ""
    },
    {
      "事项编码": "10020106",
      "事项名称": "疫苗",
      "事项分类": "基本经费",
      "是否末级": "是",
      "支出明细": "金额",
      "归口部门": "防保科",
      "归口代编": "是",
      "资本性支出": "否",
      "明细表单": "无",
      "功能分类科目": "综合医院",
      "部门经济分类": "  专用材料费",
      "政府经济分类": "",
      "现金流量": "",
      "发布方式": "一次性发布",
      "表单类型": "一般经费",
      "开支标准": "",
      "事项定义": ""
    },
    {
      "事项编码": "10020109",
      "事项名称": "其他卫生材料",
      "事项分类": "基本经费",
      "是否末级": "是",
      "支出明细": "金额",
      "归口部门": "药剂科",
      "归口代编": "否",
      "资本性支出": "否",
      "明细表单": "无",
      "功能分类科目": "综合医院",
      "部门经济分类": "  专用材料费",
      "政府经济分类": "",
      "现金流量": "",
      "发布方式": "一次性发布",
      "表单类型": "一般经费",
      "开支标准": "",
      "事项定义": ""
    },
    {
      "事项编码": "100202",
      "事项名称": "日常办公用品费",
      "事项分类": "基本经费",
      "是否末级": "否",
      "支出明细": "金额",
      "归口部门": "",
      "归口代编": "否",
      "资本性支出": "否",
      "明细表单": "无",
      "功能分类科目": "",
      "部门经济分类": "",
      "政府经济分类": "",
      "现金流量": "",
      "发布方式": "一次性发布",
      "表单类型": "一般经费",
      "开支标准": "",
      "事项定义": ""
    },
    {
      "事项编码": "10020201",
      "事项名称": "办公用品",
      "事项分类": "基本经费",
      "是否末级": "是",
      "支出明细": "金额",
      "归口部门": "总务科",
      "归口代编": "是",
      "资本性支出": "否",
      "明细表单": "无",
      "功能分类科目": "综合医院",
      "部门经济分类": "  办公费",
      "政府经济分类": "",
      "现金流量": "",
      "发布方式": "一次性发布",
      "表单类型": "一般经费",
      "开支标准": "",
      "事项定义": ""
    },
    {
      "事项编码": "10020202",
      "事项名称": "低值易耗品",
      "事项分类": "基本经费",
      "是否末级": "是",
      "支出明细": "金额",
      "归口部门": "总务科",
      "归口代编": "是",
      "资本性支出": "否",
      "明细表单": "无",
      "功能分类科目": "综合医院",
      "部门经济分类": "  办公费",
      "政府经济分类": "",
      "现金流量": "",
      "发布方式": "一次性发布",
      "表单类型": "一般经费",
      "开支标准": "",
      "事项定义": ""
    },
    {
      "事项编码": "10020299",
      "事项名称": "其他材料",
      "事项分类": "基本经费",
      "是否末级": "是",
      "支出明细": "金额",
      "归口部门": "总务科",
      "归口代编": "是",
      "资本性支出": "否",
      "明细表单": "无",
      "功能分类科目": "综合医院",
      "部门经济分类": "  其他商品和服务支出",
      "政府经济分类": "",
      "现金流量": "",
      "发布方式": "一次性发布",
      "表单类型": "一般经费",
      "开支标准": "",
      "事项定义": ""
    },
    {
      "事项编码": "100203",
      "事项名称": "药品费",
      "事项分类": "基本经费",
      "是否末级": "否",
      "支出明细": "金额",
      "归口部门": "药剂科",
      "归口代编": "否",
      "资本性支出": "",
      "明细表单": "无",
      "功能分类科目": "综合医院",
      "部门经济分类": "",
      "政府经济分类": "",
      "现金流量": "",
      "发布方式": "",
      "表单类型": "",
      "开支标准": "",
      "事项定义": ""
    },
    {
      "事项编码": "10020301",
      "事项名称": "西药",
      "事项分类": "基本经费",
      "是否末级": "是",
      "支出明细": "金额",
      "归口部门": "药剂科",
      "归口代编": "否",
      "资本性支出": "否",
      "明细表单": "无",
      "功能分类科目": "综合医院",
      "部门经济分类": "  专用材料费",
      "政府经济分类": "",
      "现金流量": "",
      "发布方式": "一次性发布",
      "表单类型": "一般经费",
      "开支标准": "",
      "事项定义": ""
    },
    {
      "事项编码": "10020302",
      "事项名称": "中成药",
      "事项分类": "基本经费",
      "是否末级": "是",
      "支出明细": "金额",
      "归口部门": "药剂科",
      "归口代编": "否",
      "资本性支出": "否",
      "明细表单": "无",
      "功能分类科目": "综合医院",
      "部门经济分类": "  专用材料费",
      "政府经济分类": "",
      "现金流量": "",
      "发布方式": "一次性发布",
      "表单类型": "一般经费",
      "开支标准": "",
      "事项定义": ""
    },
    {
      "事项编码": "10020303",
      "事项名称": "中草药",
      "事项分类": "基本经费",
      "是否末级": "是",
      "支出明细": "金额",
      "归口部门": "药剂科",
      "归口代编": "否",
      "资本性支出": "否",
      "明细表单": "无",
      "功能分类科目": "综合医院",
      "部门经济分类": "  专用材料费",
      "政府经济分类": "",
      "现金流量": "",
      "发布方式": "一次性发布",
      "表单类型": "一般经费",
      "开支标准": "",
      "事项定义": ""
    },
    {
      "事项编码": "100204",
      "事项名称": "固定资产购置费",
      "事项分类": "基本经费",
      "是否末级": "否",
      "支出明细": "金额",
      "归口部门": "",
      "归口代编": "否",
      "资本性支出": "否",
      "明细表单": "无",
      "功能分类科目": "",
      "部门经济分类": "",
      "政府经济分类": "",
      "现金流量": "",
      "发布方式": "",
      "表单类型": "一般经费",
      "开支标准": "",
      "事项定义": ""
    },
    {
      "事项编码": "10020401",
      "事项名称": "通用资产",
      "事项分类": "基本经费",
      "是否末级": "是",
      "支出明细": "数量单价",
      "归口部门": "总务科",
      "归口代编": "否",
      "资本性支出": "否",
      "明细表单": "信息化项目",
      "功能分类科目": "综合医院",
      "部门经济分类": "  办公设备购置★",
      "政府经济分类": "",
      "现金流量": "",
      "发布方式": "一次性发布",
      "表单类型": "一般经费",
      "开支标准": "",
      "事项定义": ""
    },
    {
      "事项编码": "10020402",
      "事项名称": "专用设备",
      "事项分类": "基本经费",
      "是否末级": "是",
      "支出明细": "金额",
      "归口部门": "普通外科病区",
      "归口代编": "否",
      "资本性支出": "否",
      "明细表单": "设备购置",
      "功能分类科目": "综合医院",
      "部门经济分类": "  专用设备购置★",
      "政府经济分类": "",
      "现金流量": "",
      "发布方式": "一次性发布",
      "表单类型": "一般经费",
      "开支标准": "",
      "事项定义": ""
    },
    {
      "事项编码": "10020403",
      "事项名称": "提取医疗风险基金",
      "事项分类": "基本经费",
      "是否末级": "是",
      "支出明细": "金额",
      "归口部门": "财务科",
      "归口代编": "是",
      "资本性支出": "否",
      "明细表单": "无",
      "功能分类科目": "综合医院",
      "部门经济分类": "",
      "政府经济分类": "",
      "现金流量": "",
      "发布方式": "一次性发布",
      "表单类型": "一般经费",
      "开支标准": "",
      "事项定义": ""
    },
    {
      "事项编码": "100205",
      "事项名称": "提取医疗风险基金",
      "事项分类": "基本经费",
      "是否末级": "否",
      "支出明细": "金额",
      "归口部门": "",
      "归口代编": "是",
      "资本性支出": "否",
      "明细表单": "无",
      "功能分类科目": "",
      "部门经济分类": "",
      "政府经济分类": "",
      "现金流量": "",
      "发布方式": "一次性发布",
      "表单类型": "一般经费",
      "开支标准": "",
      "事项定义": ""
    },
    {
      "事项编码": "1003",
      "事项名称": "提取医疗风险基金",
      "事项分类": "基本经费",
      "是否末级": "是",
      "支出明细": "金额",
      "归口部门": "财务科",
      "归口代编": "是",
      "资本性支出": "否",
      "明细表单": "无",
      "功能分类科目": "综合医院",
      "部门经济分类": "",
      "政府经济分类": "",
      "现金流量": "",
      "发布方式": "一次性发布",
      "表单类型": "一般经费",
      "开支标准": "",
      "事项定义": ""
    },
    {
      "事项编码": "1007",
      "事项名称": "管理费用",
      "事项分类": "基本经费",
      "是否末级": "否",
      "支出明细": "金额",
      "归口部门": "财务科",
      "归口代编": "是",
      "资本性支出": "否",
      "明细表单": "无",
      "功能分类科目": "综合医院",
      "部门经济分类": "",
      "政府经济分类": "",
      "现金流量": "",
      "发布方式": "一次性发布",
      "表单类型": "一般经费",
      "开支标准": "",
      "事项定义": ""
    },
    {
      "事项编码": "100701",
      "事项名称": "办公费",
      "事项分类": "基本经费",
      "是否末级": "是",
      "支出明细": "金额",
      "归口部门": "院办",
      "归口代编": "是",
      "资本性支出": "否",
      "明细表单": "无",
      "功能分类科目": "综合医院",
      "部门经济分类": "  办公费",
      "政府经济分类": "",
      "现金流量": "",
      "发布方式": "一次性发布",
      "表单类型": "一般经费",
      "开支标准": "",
      "事项定义": ""
    },
    {
      "事项编码": "100702",
      "事项名称": "印刷费",
      "事项分类": "基本经费",
      "是否末级": "是",
      "支出明细": "金额",
      "归口部门": "总务科",
      "归口代编": "是",
      "资本性支出": "否",
      "明细表单": "无",
      "功能分类科目": "综合医院",
      "部门经济分类": "  印刷费",
      "政府经济分类": "",
      "现金流量": "",
      "发布方式": "一次性发布",
      "表单类型": "一般经费",
      "开支标准": "",
      "事项定义": ""
    },
    {
      "事项编码": "100703",
      "事项名称": "咨询费",
      "事项分类": "基本经费",
      "是否末级": "是",
      "支出明细": "金额",
      "归口部门": "院办",
      "归口代编": "是",
      "资本性支出": "否",
      "明细表单": "无",
      "功能分类科目": "综合医院",
      "部门经济分类": "  咨询费",
      "政府经济分类": "",
      "现金流量": "",
      "发布方式": "一次性发布",
      "表单类型": "一般经费",
      "开支标准": "",
      "事项定义": ""
    },
    {
      "事项编码": "100704",
      "事项名称": "手续费",
      "事项分类": "基本经费",
      "是否末级": "是",
      "支出明细": "金额",
      "归口部门": "院办",
      "归口代编": "是",
      "资本性支出": "否",
      "明细表单": "无",
      "功能分类科目": "综合医院",
      "部门经济分类": "  手续费",
      "政府经济分类": "",
      "现金流量": "",
      "发布方式": "一次性发布",
      "表单类型": "一般经费",
      "开支标准": "",
      "事项定义": ""
    },
    {
      "事项编码": "100705",
      "事项名称": "设备购置",
      "事项分类": "基本经费",
      "是否末级": "是",
      "支出明细": "金额",
      "归口部门": "总务科",
      "归口代编": "否",
      "资本性支出": "否",
      "明细表单": "设备购置",
      "功能分类科目": "综合医院",
      "部门经济分类": "  水费",
      "政府经济分类": "",
      "现金流量": "",
      "发布方式": "一次性发布",
      "表单类型": "一般经费",
      "开支标准": "",
      "事项定义": ""
    },
    {
      "事项编码": "100706",
      "事项名称": "电费",
      "事项分类": "基本经费",
      "是否末级": "是",
      "支出明细": "金额",
      "归口部门": "总务科",
      "归口代编": "否",
      "资本性支出": "否",
      "明细表单": "无",
      "功能分类科目": "综合医院",
      "部门经济分类": "  电费",
      "政府经济分类": "",
      "现金流量": "",
      "发布方式": "一次性发布",
      "表单类型": "一般经费",
      "开支标准": "",
      "事项定义": ""
    },
    {
      "事项编码": "100707",
      "事项名称": "邮电费",
      "事项分类": "基本经费",
      "是否末级": "是",
      "支出明细": "金额",
      "归口部门": "院办",
      "归口代编": "否",
      "资本性支出": "否",
      "明细表单": "无",
      "功能分类科目": "综合医院",
      "部门经济分类": "  邮电费",
      "政府经济分类": "",
      "现金流量": "",
      "发布方式": "一次性发布",
      "表单类型": "一般经费",
      "开支标准": "",
      "事项定义": ""
    },
    {
      "事项编码": "100709",
      "事项名称": "物业管理费",
      "事项分类": "基本经费",
      "是否末级": "是",
      "支出明细": "金额",
      "归口部门": "总务科",
      "归口代编": "是",
      "资本性支出": "否",
      "明细表单": "无",
      "功能分类科目": "综合医院",
      "部门经济分类": "  物业管理费",
      "政府经济分类": "",
      "现金流量": "",
      "发布方式": "一次性发布",
      "表单类型": "一般经费",
      "开支标准": "",
      "事项定义": ""
    },
    {
      "事项编码": "100711",
      "事项名称": "差旅费",
      "事项分类": "基本经费",
      "是否末级": "是",
      "支出明细": "金额",
      "归口部门": "院办",
      "归口代编": "是",
      "资本性支出": "否",
      "明细表单": "人员进修",
      "功能分类科目": "综合医院",
      "部门经济分类": "  差旅费",
      "政府经济分类": "",
      "现金流量": "",
      "发布方式": "一次性发布",
      "表单类型": "差旅费",
      "开支标准": "",
      "事项定义": ""
    },
    {
      "事项编码": "100712",
      "事项名称": "因公出国(境)费用",
      "事项分类": "基本经费",
      "是否末级": "是",
      "支出明细": "金额",
      "归口部门": "院办",
      "归口代编": "是",
      "资本性支出": "否",
      "明细表单": "无",
      "功能分类科目": "综合医院",
      "部门经济分类": "  因公出国（境）费用",
      "政府经济分类": "",
      "现金流量": "",
      "发布方式": "一次性发布",
      "表单类型": "出国费",
      "开支标准": "定制差旅-交通",
      "事项定义": ""
    },
    {
      "事项编码": "100713",
      "事项名称": "维修（护）费",
      "事项分类": "基本经费",
      "是否末级": "是",
      "支出明细": "金额",
      "归口部门": "总务科",
      "归口代编": "是",
      "资本性支出": "否",
      "明细表单": "无",
      "功能分类科目": "综合医院",
      "部门经济分类": "  维修(护)费",
      "政府经济分类": "",
      "现金流量": "",
      "发布方式": "一次性发布",
      "表单类型": "一般经费",
      "开支标准": "",
      "事项定义": ""
    },
    {
      "事项编码": "100714",
      "事项名称": "租赁费",
      "事项分类": "基本经费",
      "是否末级": "是",
      "支出明细": "金额",
      "归口部门": "总务科",
      "归口代编": "是",
      "资本性支出": "否",
      "明细表单": "无",
      "功能分类科目": "综合医院",
      "部门经济分类": "  租赁费",
      "政府经济分类": "",
      "现金流量": "",
      "发布方式": "一次性发布",
      "表单类型": "一般经费",
      "开支标准": "",
      "事项定义": ""
    },
    {
      "事项编码": "100715",
      "事项名称": "会议费",
      "事项分类": "基本经费",
      "是否末级": "是",
      "支出明细": "金额",
      "归口部门": "院办",
      "归口代编": "是",
      "资本性支出": "否",
      "明细表单": "无",
      "功能分类科目": "综合医院",
      "部门经济分类": "  会议费",
      "政府经济分类": "",
      "现金流量": "",
      "发布方式": "一次性发布",
      "表单类型": "会议费",
      "开支标准": "会议费标准",
      "事项定义": ""
    },
    {
      "事项编码": "100716",
      "事项名称": "培训费",
      "事项分类": "基本经费",
      "是否末级": "是",
      "支出明细": "金额",
      "归口部门": "医务科",
      "归口代编": "否",
      "资本性支出": "否",
      "明细表单": "人员进修",
      "功能分类科目": "综合医院",
      "部门经济分类": "  培训费",
      "政府经济分类": "",
      "现金流量": "",
      "发布方式": "一次性发布",
      "表单类型": "培训费",
      "开支标准": "培训费标准",
      "事项定义": ""
    },
    {
      "事项编码": "100717",
      "事项名称": "公务接待费",
      "事项分类": "基本经费",
      "是否末级": "是",
      "支出明细": "金额",
      "归口部门": "院办",
      "归口代编": "是",
      "资本性支出": "否",
      "明细表单": "无",
      "功能分类科目": "综合医院",
      "部门经济分类": "  公务接待费",
      "政府经济分类": "",
      "现金流量": "",
      "发布方式": "一次性发布",
      "表单类型": "国内接待费",
      "开支标准": "公务接待标准",
      "事项定义": ""
    },
    {
      "事项编码": "100725",
      "事项名称": "专用燃料费",
      "事项分类": "基本经费",
      "是否末级": "是",
      "支出明细": "金额",
      "归口部门": "总务科",
      "归口代编": "是",
      "资本性支出": "否",
      "明细表单": "无",
      "功能分类科目": "综合医院",
      "部门经济分类": "  专用燃料费",
      "政府经济分类": "",
      "现金流量": "",
      "发布方式": "一次性发布",
      "表单类型": "一般经费",
      "开支标准": "",
      "事项定义": ""
    },
    {
      "事项编码": "100726",
      "事项名称": "劳务费",
      "事项分类": "基本经费",
      "是否末级": "是",
      "支出明细": "金额",
      "归口部门": "医务科",
      "归口代编": "是",
      "资本性支出": "否",
      "明细表单": "无",
      "功能分类科目": "综合医院",
      "部门经济分类": "  劳务费",
      "政府经济分类": "",
      "现金流量": "",
      "发布方式": "一次性发布",
      "表单类型": "劳务费",
      "开支标准": "",
      "事项定义": ""
    },
    {
      "事项编码": "100727",
      "事项名称": "委托业务费",
      "事项分类": "基本经费",
      "是否末级": "否",
      "支出明细": "金额",
      "归口部门": "",
      "归口代编": "否",
      "资本性支出": "否",
      "明细表单": "无",
      "功能分类科目": "",
      "部门经济分类": "",
      "政府经济分类": "",
      "现金流量": "",
      "发布方式": "一次性发布",
      "表单类型": "一般经费",
      "开支标准": "",
      "事项定义": ""
    },
    {
      "事项编码": "10072701",
      "事项名称": "消毒费",
      "事项分类": "基本经费",
      "是否末级": "是",
      "支出明细": "金额",
      "归口部门": "护理部",
      "归口代编": "是",
      "资本性支出": "否",
      "明细表单": "无",
      "功能分类科目": "综合医院",
      "部门经济分类": "  公务接待费",
      "政府经济分类": "",
      "现金流量": "",
      "发布方式": "一次性发布",
      "表单类型": "一般经费",
      "开支标准": "",
      "事项定义": ""
    },
    {
      "事项编码": "10072702",
      "事项名称": "洗涤费",
      "事项分类": "基本经费",
      "是否末级": "是",
      "支出明细": "金额",
      "归口部门": "总务科",
      "归口代编": "是",
      "资本性支出": "否",
      "明细表单": "无",
      "功能分类科目": "综合医院",
      "部门经济分类": "  委托业务费",
      "政府经济分类": "",
      "现金流量": "",
      "发布方式": "一次性发布",
      "表单类型": "一般经费",
      "开支标准": "",
      "事项定义": ""
    },
    {
      "事项编码": "10072703",
      "事项名称": "污水处理费",
      "事项分类": "基本经费",
      "是否末级": "是",
      "支出明细": "金额",
      "归口部门": "总务科",
      "归口代编": "是",
      "资本性支出": "否",
      "明细表单": "无",
      "功能分类科目": "综合医院",
      "部门经济分类": "  委托业务费",
      "政府经济分类": "",
      "现金流量": "",
      "发布方式": "一次性发布",
      "表单类型": "一般经费",
      "开支标准": "",
      "事项定义": ""
    },
    {
      "事项编码": "10072704",
      "事项名称": "医废处理费",
      "事项分类": "基本经费",
      "是否末级": "是",
      "支出明细": "金额",
      "归口部门": "护理部",
      "归口代编": "是",
      "资本性支出": "否",
      "明细表单": "无",
      "功能分类科目": "综合医院",
      "部门经济分类": "  委托业务费",
      "政府经济分类": "",
      "现金流量": "",
      "发布方式": "一次性发布",
      "表单类型": "一般经费",
      "开支标准": "",
      "事项定义": ""
    },
    {
      "事项编码": "10072705",
      "事项名称": "卫生及消杀费",
      "事项分类": "基本经费",
      "是否末级": "是",
      "支出明细": "金额",
      "归口部门": "护理部",
      "归口代编": "是",
      "资本性支出": "否",
      "明细表单": "无",
      "功能分类科目": "综合医院",
      "部门经济分类": "  委托业务费",
      "政府经济分类": "",
      "现金流量": "",
      "发布方式": "一次性发布",
      "表单类型": "一般经费",
      "开支标准": "",
      "事项定义": ""
    },
    {
      "事项编码": "10072706",
      "事项名称": "软件及维护费",
      "事项分类": "基本经费",
      "是否末级": "是",
      "支出明细": "金额",
      "归口部门": "院办",
      "归口代编": "是",
      "资本性支出": "否",
      "明细表单": "无",
      "功能分类科目": "综合医院",
      "部门经济分类": "  委托业务费",
      "政府经济分类": "",
      "现金流量": "",
      "发布方式": "一次性发布",
      "表单类型": "一般经费",
      "开支标准": "",
      "事项定义": ""
    },
    {
      "事项编码": "10072707",
      "事项名称": "物业服务费",
      "事项分类": "基本经费",
      "是否末级": "是",
      "支出明细": "金额",
      "归口部门": "总务科",
      "归口代编": "是",
      "资本性支出": "否",
      "明细表单": "无",
      "功能分类科目": "综合医院",
      "部门经济分类": "  委托业务费",
      "政府经济分类": "",
      "现金流量": "",
      "发布方式": "一次性发布",
      "表单类型": "一般经费",
      "开支标准": "",
      "事项定义": ""
    },
    {
      "事项编码": "10072708",
      "事项名称": "检验费",
      "事项分类": "基本经费",
      "是否末级": "是",
      "支出明细": "金额",
      "归口部门": "医务科",
      "归口代编": "是",
      "资本性支出": "否",
      "明细表单": "无",
      "功能分类科目": "综合医院",
      "部门经济分类": "  委托业务费",
      "政府经济分类": "",
      "现金流量": "",
      "发布方式": "一次性发布",
      "表单类型": "一般经费",
      "开支标准": "",
      "事项定义": ""
    },
    {
      "事项编码": "10072709",
      "事项名称": "计量仪器",
      "事项分类": "基本经费",
      "是否末级": "是",
      "支出明细": "金额",
      "归口部门": "医务科",
      "归口代编": "是",
      "资本性支出": "否",
      "明细表单": "无",
      "功能分类科目": "综合医院",
      "部门经济分类": "  委托业务费",
      "政府经济分类": "",
      "现金流量": "",
      "发布方式": "一次性发布",
      "表单类型": "一般经费",
      "开支标准": "",
      "事项定义": ""
    },
    {
      "事项编码": "10072710",
      "事项名称": "医疗鉴定费",
      "事项分类": "基本经费",
      "是否末级": "是",
      "支出明细": "金额",
      "归口部门": "医务科",
      "归口代编": "是",
      "资本性支出": "否",
      "明细表单": "无",
      "功能分类科目": "综合医院",
      "部门经济分类": "  委托业务费",
      "政府经济分类": "",
      "现金流量": "",
      "发布方式": "一次性发布",
      "表单类型": "一般经费",
      "开支标准": "",
      "事项定义": ""
    },
    {
      "事项编码": "10072711",
      "事项名称": "医用X射线机检测费",
      "事项分类": "基本经费",
      "是否末级": "是",
      "支出明细": "金额",
      "归口部门": "医务科",
      "归口代编": "是",
      "资本性支出": "否",
      "明细表单": "无",
      "功能分类科目": "综合医院",
      "部门经济分类": "  委托业务费",
      "政府经济分类": "",
      "现金流量": "",
      "发布方式": "一次性发布",
      "表单类型": "一般经费",
      "开支标准": "",
      "事项定义": ""
    },
    {
      "事项编码": "10072712",
      "事项名称": "新生儿筛查",
      "事项分类": "基本经费",
      "是否末级": "是",
      "支出明细": "金额",
      "归口部门": "医务科",
      "归口代编": "是",
      "资本性支出": "否",
      "明细表单": "无",
      "功能分类科目": "综合医院",
      "部门经济分类": "  委托业务费",
      "政府经济分类": "",
      "现金流量": "",
      "发布方式": "一次性发布",
      "表单类型": "一般经费",
      "开支标准": "",
      "事项定义": ""
    },
    {
      "事项编码": "10072799",
      "事项名称": "其他委托业务费",
      "事项分类": "基本经费",
      "是否末级": "是",
      "支出明细": "金额",
      "归口部门": "总务科",
      "归口代编": "是",
      "资本性支出": "否",
      "明细表单": "无",
      "功能分类科目": "综合医院",
      "部门经济分类": "  委托业务费",
      "政府经济分类": "",
      "现金流量": "",
      "发布方式": "一次性发布",
      "表单类型": "一般经费",
      "开支标准": "",
      "事项定义": ""
    },
    {
      "事项编码": "100728",
      "事项名称": "工会经费",
      "事项分类": "基本经费",
      "是否末级": "是",
      "支出明细": "金额",
      "归口部门": "院办",
      "归口代编": "是",
      "资本性支出": "否",
      "明细表单": "支出事项明细",
      "功能分类科目": "综合医院",
      "部门经济分类": "  工会经费",
      "政府经济分类": "",
      "现金流量": "",
      "发布方式": "一次性发布",
      "表单类型": "一般经费",
      "开支标准": "",
      "事项定义": ""
    },
    {
      "事项编码": "100729",
      "事项名称": "福利费",
      "事项分类": "基本经费",
      "是否末级": "是",
      "支出明细": "金额",
      "归口部门": "院办",
      "归口代编": "是",
      "资本性支出": "否",
      "明细表单": "无",
      "功能分类科目": "综合医院",
      "部门经济分类": "  福利费",
      "政府经济分类": "",
      "现金流量": "",
      "发布方式": "一次性发布",
      "表单类型": "一般经费",
      "开支标准": "",
      "事项定义": ""
    },
    {
      "事项编码": "100731",
      "事项名称": "公务用车运行维护费",
      "事项分类": "基本经费",
      "是否末级": "是",
      "支出明细": "金额",
      "归口部门": "总务科",
      "归口代编": "是",
      "资本性支出": "否",
      "明细表单": "无",
      "功能分类科目": "综合医院",
      "部门经济分类": "  公务用车运行维护费",
      "政府经济分类": "",
      "现金流量": "",
      "发布方式": "一次性发布",
      "表单类型": "公务用车",
      "开支标准": "",
      "事项定义": ""
    },
    {
      "事项编码": "100732",
      "事项名称": "业务用车运行维护费",
      "事项分类": "基本经费",
      "是否末级": "是",
      "支出明细": "金额",
      "归口部门": "总务科",
      "归口代编": "是",
      "资本性支出": "否",
      "明细表单": "无",
      "功能分类科目": "综合医院",
      "部门经济分类": "  其他交通费用",
      "政府经济分类": "",
      "现金流量": "",
      "发布方式": "一次性发布",
      "表单类型": "一般经费",
      "开支标准": "",
      "事项定义": ""
    },
    {
      "事项编码": "100739",
      "事项名称": "其他交通工具运行维护",
      "事项分类": "基本经费",
      "是否末级": "是",
      "支出明细": "金额",
      "归口部门": "总务科",
      "归口代编": "是",
      "资本性支出": "否",
      "明细表单": "无",
      "功能分类科目": "综合医院",
      "部门经济分类": "  其他交通费用",
      "政府经济分类": "",
      "现金流量": "",
      "发布方式": "一次性发布",
      "表单类型": "一般经费",
      "开支标准": "",
      "事项定义": ""
    },
    {
      "事项编码": "100799",
      "事项名称": "其他",
      "事项分类": "基本经费",
      "是否末级": "否",
      "支出明细": "金额",
      "归口部门": "",
      "归口代编": "是",
      "资本性支出": "",
      "明细表单": "无",
      "功能分类科目": "综合医院",
      "部门经济分类": "",
      "政府经济分类": "",
      "现金流量": "",
      "发布方式": "",
      "表单类型": "",
      "开支标准": "",
      "事项定义": ""
    },
    {
      "事项编码": "10079901",
      "事项名称": "诉讼费",
      "事项分类": "基本经费",
      "是否末级": "是",
      "支出明细": "金额",
      "归口部门": "院办",
      "归口代编": "是",
      "资本性支出": "否",
      "明细表单": "无",
      "功能分类科目": "综合医院",
      "部门经济分类": "  其他商品和服务支出",
      "政府经济分类": "",
      "现金流量": "",
      "发布方式": "一次性发布",
      "表单类型": "一般经费",
      "开支标准": "",
      "事项定义": ""
    },
    {
      "事项编码": "10079902",
      "事项名称": "律师费",
      "事项分类": "基本经费",
      "是否末级": "是",
      "支出明细": "金额",
      "归口部门": "院办",
      "归口代编": "是",
      "资本性支出": "否",
      "明细表单": "无",
      "功能分类科目": "综合医院",
      "部门经济分类": "  其他商品和服务支出",
      "政府经济分类": "",
      "现金流量": "",
      "发布方式": "一次性发布",
      "表单类型": "一般经费",
      "开支标准": "",
      "事项定义": ""
    },
    {
      "事项编码": "10079903",
      "事项名称": "提取坏帐准备",
      "事项分类": "基本经费",
      "是否末级": "是",
      "支出明细": "金额",
      "归口部门": "财务科",
      "归口代编": "是",
      "资本性支出": "否",
      "明细表单": "无",
      "功能分类科目": "综合医院",
      "部门经济分类": "  其他商品和服务支出",
      "政府经济分类": "",
      "现金流量": "",
      "发布方式": "一次性发布",
      "表单类型": "一般经费",
      "开支标准": "",
      "事项定义": ""
    },
    {
      "事项编码": "10079904",
      "事项名称": "工作餐费",
      "事项分类": "基本经费",
      "是否末级": "是",
      "支出明细": "金额",
      "归口部门": "人事科",
      "归口代编": "是",
      "资本性支出": "否",
      "明细表单": "无",
      "功能分类科目": "综合医院",
      "部门经济分类": "  其他商品和服务支出",
      "政府经济分类": "",
      "现金流量": "",
      "发布方式": "一次性发布",
      "表单类型": "一般经费",
      "开支标准": "",
      "事项定义": ""
    },
    {
      "事项编码": "10079905",
      "事项名称": "宣传费",
      "事项分类": "基本经费",
      "是否末级": "是",
      "支出明细": "金额",
      "归口部门": "党办",
      "归口代编": "是",
      "资本性支出": "否",
      "明细表单": "无",
      "功能分类科目": "综合医院",
      "部门经济分类": "  其他商品和服务支出",
      "政府经济分类": "",
      "现金流量": "",
      "发布方式": "一次性发布",
      "表单类型": "一般经费",
      "开支标准": "",
      "事项定义": ""
    },
    {
      "事项编码": "10079906",
      "事项名称": "健康教育费",
      "事项分类": "基本经费",
      "是否末级": "是",
      "支出明细": "金额",
      "归口部门": "科教科",
      "归口代编": "是",
      "资本性支出": "否",
      "明细表单": "无",
      "功能分类科目": "综合医院",
      "部门经济分类": "  其他商品和服务支出",
      "政府经济分类": "",
      "现金流量": "",
      "发布方式": "一次性发布",
      "表单类型": "一般经费",
      "开支标准": "",
      "事项定义": ""
    },
    {
      "事项编码": "10079909",
      "事项名称": "医疗纠纷补助",
      "事项分类": "基本经费",
      "是否末级": "是",
      "支出明细": "金额",
      "归口部门": "医务科",
      "归口代编": "是",
      "资本性支出": "否",
      "明细表单": "无",
      "功能分类科目": "综合医院",
      "部门经济分类": "  其他商品和服务支出",
      "政府经济分类": "",
      "现金流量": "",
      "发布方式": "一次性发布",
      "表单类型": "一般经费",
      "开支标准": "",
      "事项定义": ""
    },
    {
      "事项编码": "10079910",
      "事项名称": "科研费",
      "事项分类": "基本经费",
      "是否末级": "是",
      "支出明细": "金额",
      "归口部门": "科教科",
      "归口代编": "是",
      "资本性支出": "否",
      "明细表单": "无",
      "功能分类科目": "综合医院",
      "部门经济分类": "  其他商品和服务支出",
      "政府经济分类": "",
      "现金流量": "",
      "发布方式": "一次性发布",
      "表单类型": "一般经费",
      "开支标准": "",
      "事项定义": ""
    },
    {
      "事项编码": "10079911",
      "事项名称": "教学费",
      "事项分类": "基本经费",
      "是否末级": "否",
      "支出明细": "金额",
      "归口部门": "",
      "归口代编": "否",
      "资本性支出": "否",
      "明细表单": "无",
      "功能分类科目": "",
      "部门经济分类": "",
      "政府经济分类": "",
      "现金流量": "",
      "发布方式": "一次性发布",
      "表单类型": "一般经费",
      "开支标准": "",
      "事项定义": ""
    },
    {
      "事项编码": "1007991101",
      "事项名称": "中山医合作费",
      "事项分类": "基本经费",
      "是否末级": "是",
      "支出明细": "金额",
      "归口部门": "科教科",
      "归口代编": "是",
      "资本性支出": "否",
      "明细表单": "无",
      "功能分类科目": "综合医院",
      "部门经济分类": "  其他商品和服务支出",
      "政府经济分类": "",
      "现金流量": "",
      "发布方式": "一次性发布",
      "表单类型": "一般经费",
      "开支标准": "",
      "事项定义": ""
    },
    {
      "事项编码": "1007991109",
      "事项名称": "其他教学费",
      "事项分类": "基本经费",
      "是否末级": "是",
      "支出明细": "金额",
      "归口部门": "科教科",
      "归口代编": "是",
      "资本性支出": "否",
      "明细表单": "无",
      "功能分类科目": "综合医院",
      "部门经济分类": "  其他商品和服务支出",
      "政府经济分类": "",
      "现金流量": "",
      "发布方式": "一次性发布",
      "表单类型": "一般经费",
      "开支标准": "",
      "事项定义": ""
    },
    {
      "事项编码": "10079912",
      "事项名称": "专项经费支出",
      "事项分类": "基本经费",
      "是否末级": "是",
      "支出明细": "金额",
      "归口部门": "科教科",
      "归口代编": "是",
      "资本性支出": "否",
      "明细表单": "无",
      "功能分类科目": "综合医院",
      "部门经济分类": "  其他商品和服务支出",
      "政府经济分类": "",
      "现金流量": "",
      "发布方式": "一次性发布",
      "表单类型": "一般经费",
      "开支标准": "",
      "事项定义": ""
    },
    {
      "事项编码": "10079913",
      "事项名称": "招牌制作费",
      "事项分类": "基本经费",
      "是否末级": "是",
      "支出明细": "金额",
      "归口部门": "总务科",
      "归口代编": "是",
      "资本性支出": "否",
      "明细表单": "无",
      "功能分类科目": "综合医院",
      "部门经济分类": "  其他商品和服务支出",
      "政府经济分类": "",
      "现金流量": "",
      "发布方式": "一次性发布",
      "表单类型": "一般经费",
      "开支标准": "",
      "事项定义": ""
    },
    {
      "事项编码": "10079914",
      "事项名称": "专项业务费",
      "事项分类": "基本经费",
      "是否末级": "是",
      "支出明细": "金额",
      "归口部门": "院办",
      "归口代编": "是",
      "资本性支出": "否",
      "明细表单": "无",
      "功能分类科目": "综合医院",
      "部门经济分类": "  其他商品和服务支出",
      "政府经济分类": "",
      "现金流量": "",
      "发布方式": "一次性发布",
      "表单类型": "一般经费",
      "开支标准": "",
      "事项定义": ""
    },
    {
      "事项编码": "10079999",
      "事项名称": "其他费用",
      "事项分类": "基本经费",
      "是否末级": "是",
      "支出明细": "金额",
      "归口部门": "院办",
      "归口代编": "是",
      "资本性支出": "否",
      "明细表单": "无",
      "功能分类科目": "综合医院",
      "部门经济分类": "  其他商品和服务支出",
      "政府经济分类": "",
      "现金流量": "",
      "发布方式": "一次性发布",
      "表单类型": "一般经费",
      "开支标准": "",
      "事项定义": ""
    },
    {
      "事项编码": "1040",
      "事项名称": "其他支出",
      "事项分类": "基本经费",
      "是否末级": "否",
      "支出明细": "金额",
      "归口部门": "院办",
      "归口代编": "",
      "资本性支出": "",
      "明细表单": "无",
      "功能分类科目": "综合医院",
      "部门经济分类": "",
      "政府经济分类": "",
      "现金流量": "",
      "发布方式": "",
      "表单类型": "",
      "开支标准": "",
      "事项定义": ""
    },
    {
      "事项编码": "104001",
      "事项名称": "罚款支出",
      "事项分类": "基本经费",
      "是否末级": "是",
      "支出明细": "金额",
      "归口部门": "财务科",
      "归口代编": "是",
      "资本性支出": "否",
      "明细表单": "无",
      "功能分类科目": "综合医院",
      "部门经济分类": "  其他商品和服务支出",
      "政府经济分类": "",
      "现金流量": "",
      "发布方式": "一次性发布",
      "表单类型": "一般经费",
      "开支标准": "",
      "事项定义": ""
    },
    {
      "事项编码": "104002",
      "事项名称": "赞助支出",
      "事项分类": "基本经费",
      "是否末级": "是",
      "支出明细": "金额",
      "归口部门": "财务科",
      "归口代编": "是",
      "资本性支出": "否",
      "明细表单": "无",
      "功能分类科目": "综合医院",
      "部门经济分类": "  其他商品和服务支出",
      "政府经济分类": "",
      "现金流量": "",
      "发布方式": "一次性发布",
      "表单类型": "一般经费",
      "开支标准": "",
      "事项定义": ""
    },
    {
      "事项编码": "104003",
      "事项名称": "财产物资盘亏支出",
      "事项分类": "基本经费",
      "是否末级": "是",
      "支出明细": "金额",
      "归口部门": "财务科",
      "归口代编": "是",
      "资本性支出": "否",
      "明细表单": "无",
      "功能分类科目": "综合医院",
      "部门经济分类": "  其他商品和服务支出",
      "政府经济分类": "",
      "现金流量": "",
      "发布方式": "一次性发布",
      "表单类型": "一般经费",
      "开支标准": "",
      "事项定义": ""
    },
    {
      "事项编码": "104004",
      "事项名称": "捐赠支出",
      "事项分类": "基本经费",
      "是否末级": "是",
      "支出明细": "金额",
      "归口部门": "财务科",
      "归口代编": "是",
      "资本性支出": "否",
      "明细表单": "无",
      "功能分类科目": "",
      "部门经济分类": "对国内赠与",
      "政府经济分类": "",
      "现金流量": "",
      "发布方式": "一次性发布",
      "表单类型": "一般经费",
      "开支标准": "",
      "事项定义": ""
    },
    {
      "事项编码": "104005",
      "事项名称": "医保违规扣款",
      "事项分类": "基本经费",
      "是否末级": "是",
      "支出明细": "金额",
      "归口部门": "医务科",
      "归口代编": "是",
      "资本性支出": "否",
      "明细表单": "无",
      "功能分类科目": "综合医院",
      "部门经济分类": "  其他商品和服务支出",
      "政府经济分类": "",
      "现金流量": "",
      "发布方式": "一次性发布",
      "表单类型": "一般经费",
      "开支标准": "",
      "事项定义": ""
    },
    {
      "事项编码": "104006",
      "事项名称": "医管局科研经费支出",
      "事项分类": "基本经费",
      "是否末级": "是",
      "支出明细": "金额",
      "归口部门": "财务科",
      "归口代编": "是",
      "资本性支出": "否",
      "明细表单": "无",
      "功能分类科目": "",
      "部门经济分类": "",
      "政府经济分类": "",
      "现金流量": "",
      "发布方式": "一次性发布",
      "表单类型": "一般经费",
      "开支标准": "",
      "事项定义": ""
    },
    {
      "事项编码": "104090",
      "事项名称": "特别贡献奖金",
      "事项分类": "基本经费",
      "是否末级": "是",
      "支出明细": "金额",
      "归口部门": "院办",
      "归口代编": "是",
      "资本性支出": "否",
      "明细表单": "无",
      "功能分类科目": "",
      "部门经济分类": "",
      "政府经济分类": "",
      "现金流量": "",
      "发布方式": "一次性发布",
      "表单类型": "一般经费",
      "开支标准": "",
      "事项定义": ""
    },
    {
      "事项编码": "104091",
      "事项名称": "青年基金",
      "事项分类": "基本经费",
      "是否末级": "是",
      "支出明细": "金额",
      "归口部门": "院办",
      "归口代编": "否",
      "资本性支出": "否",
      "明细表单": "无",
      "功能分类科目": "",
      "部门经济分类": "",
      "政府经济分类": "",
      "现金流量": "",
      "发布方式": "一次性发布",
      "表单类型": "一般经费",
      "开支标准": "",
      "事项定义": ""
    }
  ]
}